ec/bucketutil.py
ec/check_sitemap.py
ec/ec_reports.py
ec/generate_graph_stats.py
ec/missing_report.py
ec/query_graph.py
ec/summarize_from_graph_namespace.py
ec/summarize_from_release.py
ec/summarize_identifier_metadata.py
ec/summarize_repo.py
ec/transform_sitemap.py
ec/collection/__init__.py
ec/collection/rocrate_archive.py
ec/collection/rocrate_collection.py
ec/datastore/__init__.py
ec/datastore/s3.py
ec/gleanerio/__init__.py
ec/gleanerio/gleaner.py
ec/graph/__init__.py
ec/graph/manageGraph.py
ec/graph/release_graph.py
ec/graph/sparql_query.py
ec/graph/sparql_files/__init__.py
ec/graph/sparql_files/all_count_datasets.sparql
ec/graph/sparql_files/all_count_keywords.sparql
ec/graph/sparql_files/all_count_multiple_versioned_datasets.sparql
ec/graph/sparql_files/all_count_triples.sparql
ec/graph/sparql_files/all_count_types.sparql
ec/graph/sparql_files/all_count_types_top_level.sparql
ec/graph/sparql_files/all_count_variablename.sparql
ec/graph/sparql_files/all_graph_sizes.sparql
ec/graph/sparql_files/all_repo_count_datasets.sparql
ec/graph/sparql_files/all_repo_count_graphs.sparql
ec/graph/sparql_files/all_repo_count_keywords.sparql
ec/graph/sparql_files/all_repo_count_types.sparql
ec/graph/sparql_files/all_repo_count_versioned_datasets.sparql
ec/graph/sparql_files/all_repo_with_keywords.sparql
ec/graph/sparql_files/all_select_datasets.sparql
ec/graph/sparql_files/all_select_graphs.sparql
ec/graph/sparql_files/all_summary_query.sparql
ec/graph/sparql_files/all_urn_w_types_toplevel.sparql
ec/graph/sparql_files/all_versioned_datasets_multiple_versions.sparql
ec/graph/sparql_files/org_all_org_triples.sparql
ec/graph/sparql_files/org_all_returns_properties.sparql
ec/graph/sparql_files/org_all_returns_urns.sparql
ec/graph/sparql_files/q_n_o_exact_query__returns_properties.sparql
ec/graph/sparql_files/q_n_o_query_returns_urn.sparql
ec/graph/sparql_files/repo_count_datasets.sparql
ec/graph/sparql_files/repo_count_graphs.sparql
earthcube_utilities-0.1.28.dist-info/METADATA
earthcube_utilities-0.1.28.dist-info/WHEEL
earthcube_utilities-0.1.28.dist-info/entry_points.txt
earthcube_utilities-0.1.28.dist-info/top_level.txt
earthcube_utilities-0.1.28.dist-info/RECORD
