Metadata-Version: 2.1
Name: earthcube_utilities
Version: 0.1.28
Summary: A package of utilities for NSF Earthcube Geocodes Project
Author-email: Mike Bobak <mbobak@illinois.edu>, David Valentine <dwvalentine@ucsd.edu>, Ya-Lan Yang <ylyang@illinois.edu>
Maintainer-email: Ya-Lan Yang <ylyang@illinois.edu>, David Valentine <dwvalentine@ucsd.edu>
Project-URL: Homepage, https://www.earthcube.org/
Project-URL: Bug Tracker, https://github.com/earthcube/earthcube_utilities/issues
Project-URL: Geocodes Documentation, https://earthcube.github.io/geocodes_documentation/
Project-URL: Source, https://github.com/earthcube/earthcube_utilities
Classifier: Development Status :: 3 - Alpha
Classifier: Intended Audience :: Science/Research
Classifier: Topic :: Software Development :: Libraries :: Python Modules
Classifier: Topic :: Scientific/Engineering
Classifier: Programming Language :: Python :: 3
Classifier: License :: OSI Approved :: MIT License
Classifier: Operating System :: OS Independent
Requires-Dist: pandas==2.2.2
Requires-Dist: rdflib==7.0.0
Requires-Dist: requests==2.28.2
Requires-Dist: simplejson==3.18.3
Requires-Dist: sparqldataframe==0.1.0
Requires-Dist: numpy>=2.0.0
Requires-Dist: minio
Requires-Dist: pyld
Requires-Dist: rocrate
Requires-Dist: rocrateValidator
Requires-Dist: uuid
Requires-Dist: logconfig
Requires-Dist: jsonschema
Requires-Dist: pydash
Requires-Dist: advertools
Requires-Dist: pandarallel
Requires-Dist: pyoxigraph
Requires-Dist: oxrdflib
Provides-Extra: dev
Requires-Dist: approvaltests; extra == "dev"
Requires-Dist: kglab; extra == "dev"
Requires-Dist: reportlab; extra == "dev"
Requires-Dist: seaborn; extra == "dev"
Requires-Dist: jupyterlab; extra == "dev"
